sincpro_siat_soap/__init__.py
sincpro_siat_soap/adapters/__init__.py
sincpro_siat_soap/adapters/siat_exception_builder.py
sincpro_siat_soap/adapters/soap.py
sincpro_siat_soap/conf/soap_siat.yml
sincpro_siat_soap/config.py
sincpro_siat_soap/domain/__init__.py
sincpro_siat_soap/domain/codes.py
sincpro_siat_soap/domain/sector_document.py
sincpro_siat_soap/domain/siat_template.py
sincpro_siat_soap/download_wsdl.py
sincpro_siat_soap/global_definitions.py
sincpro_siat_soap/infrastructure/__init__.py
sincpro_siat_soap/infrastructure/encoding.py
sincpro_siat_soap/infrastructure/encryption.py
sincpro_siat_soap/infrastructure/fn_xml.py
sincpro_siat_soap/infrastructure/soap_client.py
sincpro_siat_soap/logger.py
sincpro_siat_soap/resources/siat_xsd/SignatureSchema.xsd
sincpro_siat_soap/resources/siat_xsd/facturaComputarizadaAlquilerBienInmueble.xsd
sincpro_siat_soap/resources/siat_xsd/facturaComputarizadaAlquilerBienInmueble.xsd:Zone.Identifier
sincpro_siat_soap/resources/siat_xsd/facturaComputarizadaHospitalClinica.xsd
sincpro_siat_soap/resources/siat_xsd/facturaComputarizadaHotel.xsd
sincpro_siat_soap/resources/siat_xsd/facturaComputarizadaPrevalorada.xsd
sincpro_siat_soap/resources/siat_xsd/facturaComputarizadaSectorEducativo.xsd
sincpro_siat_soap/resources/siat_xsd/facturaElectronicaAlquilerBienInmueble.xsd
sincpro_siat_soap/resources/siat_xsd/facturaElectronicaAlquilerBienInmueble.xsd:Zone.Identifier
sincpro_siat_soap/resources/siat_xsd/facturaElectronicaCompraVenta.xsd
sincpro_siat_soap/resources/siat_xsd/facturaElectronicaHospitalClinica.xsd
sincpro_siat_soap/resources/siat_xsd/facturaElectronicaHotel.xsd
sincpro_siat_soap/resources/siat_xsd/facturaElectronicaPrevalorada.xsd
sincpro_siat_soap/resources/siat_xsd/facturaElectronicaSectorEducativo.xsd
sincpro_siat_soap/resources/siat_xsd/notaElectronicaCreditoDebito.xsd
sincpro_siat_soap/resources/wsdl/production/COMPRAS.wsdl
sincpro_siat_soap/resources/wsdl/production/FACTURA_COMPRA_VENTA.wsdl
sincpro_siat_soap-7.1.3.dist-info/METADATA
sincpro_siat_soap-7.1.3.dist-info/WHEEL
sincpro_siat_soap-7.1.3.dist-info/licenses/LICENSE.md
sincpro_siat_soap-7.1.3.dist-info/RECORD
