Metadata-Version: 2.4
Name: sincpro-siat-soap
Version: 7.1.3
Summary: Bridge SOAP Services for SIAT Bolivia
License: SINCPRO S.R.L.
License-File: LICENSE.md
Author: Gutierrez, Andres
Author-email: andru1236@gmail.com
Requires-Python: >=3.12,<4.0
Classifier: License :: Other/Proprietary License
Classifier: Programming Language :: Python :: 3
Classifier: Programming Language :: Python :: 3.12
Classifier: Programming Language :: Python :: 3.13
Classifier: Programming Language :: Python :: 3.14
Requires-Dist: python-dotenv (>=1.2.1,<2.0.0)
Requires-Dist: signxml (>=4.2.0,<5.0.0)
Requires-Dist: sincpro-framework (>=3.0.6,<4.0.0)
Requires-Dist: xmltodict (>=1.0.2,<2.0.0)
Requires-Dist: zeep (>=4.3.2,<5.0.0)
